[
  {
    "first_name": "Kort",
    "last_name": "Kalewe",
    "gender": "Male",
    "phone": "8301024727",
    "medicalRecord": "6425602872",
    "birthDate": "1978-01-31",
    "UserId": 1
  },
  {
    "first_name": "Kamillah",
    "last_name": "Echelle",
    "gender": "Female",
    "phone": "1532887002",
    "medicalRecord": "0872508986",
    "birthDate": "1986-01-21",
    "UserId": 2
  },
  {
    "first_name": "Barbe",
    "last_name": "Fante",
    "gender": "Female",
    "phone": "4365011506",
    "medicalRecord": "2099861684",
    "birthDate": "1960-01-07",
    "UserId": 3
  },
  {
    "first_name": "Gallagher",
    "last_name": "Worssam",
    "gender": "Male",
    "phone": "5264782995",
    "medicalRecord": "7562667233",
    "birthDate": "1981-02-21",
    "UserId": 4
  },
  {
    "first_name": "Clarke",
    "last_name": "Zupo",
    "gender": "Male",
    "phone": "6699034352",
    "medicalRecord": "9166937078",
    "birthDate": "1953-11-03",
    "UserId": 5
  },
  {
    "first_name": "Merna",
    "last_name": "Attfield",
    "gender": "Female",
    "phone": "1804543687",
    "medicalRecord": "1630227110",
    "birthDate": "1985-03-01",
    "UserId": 6
  },
  {
    "first_name": "Frankie",
    "last_name": "Quilleash",
    "gender": "Male",
    "phone": "1798365051",
    "medicalRecord": "8331030540",
    "birthDate": "1980-02-07",
    "UserId": 7
  },
  {
    "first_name": "Mariann",
    "last_name": "Floch",
    "gender": "Female",
    "phone": "2689892270",
    "medicalRecord": "0826966861",
    "birthDate": "1982-01-07",
    "UserId": 8
  },
  {
    "first_name": "Ashien",
    "last_name": "Kobieriecki",
    "gender": "Female",
    "phone": "7411344445",
    "medicalRecord": "9518581703",
    "birthDate": "1964-06-11",
    "UserId": 9
  },
  {
    "first_name": "Alphard",
    "last_name": "Vasse",
    "gender": "Male",
    "phone": "5798904931",
    "medicalRecord": "3000413820",
    "birthDate": "1961-03-29",
    "UserId": 10
  }
]